yolo5face/__init__.py
yolo5face/get_model.py
yolo5face/yoloface/YoloDetectorAggregator.py
yolo5face/yoloface/__init__.py
yolo5face/yoloface/face_detector.py
yolo5face/yoloface/types.py
yolo5face/yoloface/models/__init__.py
yolo5face/yoloface/models/common.py
yolo5face/yoloface/models/experimental.py
yolo5face/yoloface/models/yolo.py
yolo5face/yoloface/utils/__init__.py
yolo5face/yoloface/utils/autoanchor.py
yolo5face/yoloface/utils/datasets.py
yolo5face/yoloface/utils/general.py
yolo5face/yoloface/utils/torch_utils.py
yolo5face-0.0.10.dist-info/LICENSE
yolo5face-0.0.10.dist-info/METADATA
yolo5face-0.0.10.dist-info/WHEEL
yolo5face-0.0.10.dist-info/top_level.txt
yolo5face-0.0.10.dist-info/RECORD
