Metadata-Version: 2.1
Name: yolo5face
Version: 0.0.10
Summary: Wrapper over Yolo5Face for a more convenient inference.
Home-page: https://github.com/ternaus/yolov5faceInference
Author: Vladimir Iglovikov
License: MIT
Classifier: License :: OSI Approved :: MIT License
Classifier: Intended Audience :: Developers
Classifier: Intended Audience :: Science/Research
Classifier: Operating System :: OS Independent
Classifier: Programming Language :: Python
Classifier: Programming Language :: Python :: 3
Classifier: Topic :: Software Development :: Libraries
Classifier: Topic :: Software Development :: Libraries :: Python Modules
License-File: LICENSE
Requires-Dist: joblib (>=1.3.2)
Requires-Dist: opencv-python-headless (>=4.8.1.78)
Requires-Dist: torch (>=2.1.1)
Requires-Dist: torchvision (>=0.16.1)
Provides-Extra: test
Requires-Dist: pytest ; extra == 'test'
